README.md
setup.py
html_builder/Element.py
html_builder/EmptyElement.py
html_builder/ExistElement.py
html_builder/Html.py
html_builder/__init__.py
html_builder.egg-info/PKG-INFO
html_builder.egg-info/SOURCES.txt
html_builder.egg-info/dependency_links.txt
html_builder.egg-info/entry_points.txt
html_builder.egg-info/top_level.txt
html_builder/Body/Anchor.py
html_builder/Body/Body.py
html_builder/Body/FontElement.py
html_builder/Body/Heading.py
html_builder/Body/Image.py
html_builder/Body/Items.py
html_builder/Body/Paragraph.py
html_builder/Body/Table.py
html_builder/Body/Text.py
html_builder/Body/__init__.py
html_builder/Body/Input/Form.py
html_builder/Body/Input/Input.py
html_builder/Body/Input/IpBox.py
html_builder/Body/Input/IpButton.py
html_builder/Body/Input/IpText.py
html_builder/Body/Input/__init__.py
html_builder/Head/Head.py
html_builder/Head/Meta.py
html_builder/Head/Title.py
html_builder/Head/__init__.py